odoo/addons/pos_escpos_status/README.rst
odoo/addons/pos_escpos_status/__init__.py
odoo/addons/pos_escpos_status/__manifest__.py
odoo/addons/pos_escpos_status/i18n/it.po
odoo/addons/pos_escpos_status/i18n/pos_escpos_status.pot
odoo/addons/pos_escpos_status/readme/DESCRIPTION.rst
odoo/addons/pos_escpos_status/static/description/icon.png
odoo/addons/pos_escpos_status/static/description/index.html
odoo/addons/pos_escpos_status/static/src/js/ProxyStatus.js
odoo/addons/pos_escpos_status/views/assets.xml
odoo14_addon_pos_escpos_status-14.0.1.0.1.dev5.dist-info/METADATA
odoo14_addon_pos_escpos_status-14.0.1.0.1.dev5.dist-info/WHEEL
odoo14_addon_pos_escpos_status-14.0.1.0.1.dev5.dist-info/top_level.txt
odoo14_addon_pos_escpos_status-14.0.1.0.1.dev5.dist-info/RECORD
